myselfpyy.py
setup.py
myselfpyy.egg-info/PKG-INFO
myselfpyy.egg-info/SOURCES.txt
myselfpyy.egg-info/dependency_links.txt
myselfpyy.egg-info/top_level.txt