Metadata-Version: 2.1
Name: myselfpyy
Version: 1.0.1
Summary: a smaple distution
Home-page: http://myselff.com
Author: myselff
Author-email: myselff@qq.com
License: UNKNOWN
Platform: UNKNOWN
